{
  "extends": "nl",
  "source": "Royals forum NL guides (Darko 2024, Comprehensive, Gearing Discussion)",
  "baseStats": {
    "STR": 4,
    "DEX": 4,
    "INT": 4,
    "LUK": 943
  },
  "gearBreakdown": {
    "weapon": {
      "LUK": 3,
      "WATK": 91
    },
    "helmet": {
      "LUK": 22,
      "DEX": 40
    },
    "top": {
      "LUK": 28,
      "DEX": 5
    },
    "bottom": {
      "LUK": 10,
      "DEX": 18
    },
    "earring": {
      "LUK": 9,
      "DEX": 12
    },
    "eye": {
      "LUK": 3,
      "DEX": 3
    },
    "face": {
      "LUK": 8,
      "DEX": 5
    },
    "pendant": {
      "LUK": 27,
      "DEX": 27
    },
    "belt": {
      "LUK": 3,
      "DEX": 9
    },
    "medal": {
      "WATK": 3
    },
    "ring1": {
      "LUK": 3
    },
    "ring2": {
      "LUK": 5,
      "DEX": 5
    },
    "ring3": {
      "LUK": 5,
      "DEX": 2
    },
    "ring4": {
      "WATK": 1
    }
  }
}
